ngram_punctuator/__init__.py
ngram_punctuator/cli.py
ngram_punctuator/punctuator.py
ngram_punctuator/tokenizer.py
ngram_punctuator/utils.py
ngram_punctuator-0.0.2.dist-info/licenses/LICENSE
ngram_punctuator-0.0.2.dist-info/METADATA
ngram_punctuator-0.0.2.dist-info/WHEEL
ngram_punctuator-0.0.2.dist-info/entry_points.txt
ngram_punctuator-0.0.2.dist-info/top_level.txt
ngram_punctuator-0.0.2.dist-info/RECORD
