Metadata-Version: 2.4
Name: ngram-punctuator
Version: 0.0.2
Summary: N-gram Punctuator
Author-email: Zhendong Peng <pzd17@tsinghua.org.cn>
License:                                  Apache License
Project-URL: Homepage, https://github.com/pengzhendong/ngram-punctuator
Project-URL: Documentation, https://github.com/pengzhendong/ngram-punctuator#readme
Project-URL: BugTracker, https://github.com/pengzhendong/ngram-punctuator/issues
Classifier: Programming Language :: Python :: 3
Classifier: Operating System :: OS Independent
Requires-Python: >=3.7
License-File: LICENSE
Requires-Dist: click
Requires-Dist: kenlm
Requires-Dist: modelscope
Requires-Dist: regex
Dynamic: license-file
